CHANGELOG.txt
LICENSE
MANIFEST.in
README.md
requirements.txt
setup.py
tox.ini
touchosc2midi/__init__.py
touchosc2midi/advertise.py
touchosc2midi/configuration.py
touchosc2midi/touchosc2midi.py
touchosc2midi.egg-info/PKG-INFO
touchosc2midi.egg-info/SOURCES.txt
touchosc2midi.egg-info/dependency_links.txt
touchosc2midi.egg-info/entry_points.txt
touchosc2midi.egg-info/requires.txt
touchosc2midi.egg-info/top_level.txt