Metadata-Version: 1.1
Name: touchosc2midi
Version: 0.0.10
Summary: TouchOSC Bridge clone in python
Home-page: https://github.com/velolala/touchosc2midi
Author: velolala
Author-email: fiets@einstueckheilewelt.de
License: LICENSE
Platform: UNKNOWN
Classifier: Development Status :: 4 - Beta
Classifier: Environment :: Console
Classifier: License :: OSI Approved :: MIT License
Classifier: Operating System :: POSIX :: Linux
Classifier: Topic :: Artistic Software
Classifier: Topic :: Home Automation
Classifier: Topic :: Multimedia :: Sound/Audio :: MIDI
